wagtailmodelchooser/__init__.py
wagtailmodelchooser/blocks.py
wagtailmodelchooser/utils.py
wagtailmodelchooser/version.py
wagtailmodelchooser/viewsets.py
wagtailmodelchooser/wagtail_hooks.py
wagtailmodelchooser/static/wagtailmodelchooser/js/model_chooser.js
wagtailmodelchooser/static/wagtailmodelchooser/js/model_chooser_telepath.js
wagtailmodelchooser/templates/wagtailmodelchooser/modal.html
wagtailmodelchooser/templates/wagtailmodelchooser/model_chooser.html
wagtailmodelchooser/templates/wagtailmodelchooser/results.html
wagtail_modelchooser-4.0.1.dist-info/LICENSE
wagtail_modelchooser-4.0.1.dist-info/METADATA
wagtail_modelchooser-4.0.1.dist-info/WHEEL
wagtail_modelchooser-4.0.1.dist-info/top_level.txt
wagtail_modelchooser-4.0.1.dist-info/RECORD
