Metadata-Version: 2.1
Name: wagtail-modelchooser
Version: 4.0.1
Summary: Model choosers for Wagtail admin
Home-page: https://github.com/takeflight/wagtailmodelchooser/
Author: Tim Heap
Author-email: developers@neonjungle.studio
License: BSD License
Platform: UNKNOWN
Classifier: Environment :: Web Environment
Classifier: Intended Audience :: Developers
Classifier: Operating System :: OS Independent
Classifier: Programming Language :: Python
Classifier: Programming Language :: Python :: 3
Classifier: Programming Language :: Python :: 3.7
Classifier: Programming Language :: Python :: 3.8
Classifier: Programming Language :: Python :: 3.9
Classifier: Programming Language :: Python :: 3.10
Classifier: Framework :: Django
Classifier: License :: OSI Approved :: BSD License
License-File: LICENSE
Requires-Dist: wagtail (>=4.0)
